pypwsafe/__init__.py
pypwsafe/password_manager.py
pypwsafe/password_safe.py
pypwsafe/text_wrappers.py
py_pwsafe-2.0.3.dist-info/LICENSE
py_pwsafe-2.0.3.dist-info/METADATA
py_pwsafe-2.0.3.dist-info/WHEEL
py_pwsafe-2.0.3.dist-info/entry_points.txt
py_pwsafe-2.0.3.dist-info/top_level.txt
py_pwsafe-2.0.3.dist-info/RECORD
