Metadata-Version: 2.1
Name: py-pwsafe
Version: 2.0.3
Summary: Python Password Safe
Home-page: https://github.com/rvthai/python-passwordsafe
Author: Ricky Thai
Author-email: rickyvanthai@gmail.com
License: MIT
Platform: UNKNOWN
Classifier: Programming Language :: Python :: 3
Classifier: License :: OSI Approved :: MIT License
Classifier: Operating System :: OS Independent
Requires-Python: >=3.6
Requires-Dist: bcrypt
Requires-Dist: pyperclip
Requires-Dist: cryptography
